[{"mapId":"75500294","area":"Montagne des Koalaks","areaId":28,"subArea":"Lacs enchantés","subAreaId":231,"right":{"mapId":"147849222"}},{"mapId":"75500805","area":"Montagne des Koalaks","areaId":28,"subArea":"Lacs enchantés","subAreaId":231,"right":{"mapId":"147849735"},"top":{"mapId":"147849222"}},{"mapId":"75500804","area":"Montagne des Koalaks","areaId":28,"subArea":"Lacs enchantés","subAreaId":231,"right":{"mapId":"147849736"}},{"mapId":"73403140","area":"Montagne des Koalaks","areaId":28,"subArea":"Lacs enchantés","subAreaId":231,"top":{"mapId":"147850763"}},{"mapId":"75501826","area":"Montagne des Koalaks","areaId":28,"subArea":"Lacs enchantés","subAreaId":231,"top":{"mapId":"147850249"}},{"mapId":"75501314","area":"Montagne des Koalaks","areaId":28,"subArea":"Lacs enchantés","subAreaId":231},{"mapId":"75501315","area":"Montagne des Koalaks","areaId":28,"subArea":"Lacs enchantés","subAreaId":231,"top":{"mapId":"147849736"}},{"mapId":"75498762","area":"Montagne des Koalaks","areaId":28,"subArea":"Lacs enchantés","subAreaId":231,"top":{"mapId":"164365334"}}]