[{"mapId":"189531150","area":"Astrub","areaId":18,"subArea":"Forêt d'Astrub","subAreaId":97,"left":{"mapId":"189530638"},"right":{"mapId":"188743687"},"top":{"mapId":"189531149"},"bottom":{"mapId":"189530638"}},{"mapId":"189531149","area":"Astrub","areaId":18,"subArea":"Forêt d'Astrub","subAreaId":97,"left":{"mapId":"189530637"},"right":{"mapId":"188743686"},"top":{"mapId":"189531148"},"bottom":{"mapId":"189531150"}},{"mapId":"189531147","area":"Astrub","areaId":18,"subArea":"Forêt d'Astrub","subAreaId":97,"left":{"mapId":"189530635"},"right":{"mapId":"188743684"},"top":{"mapId":"189531146"},"bottom":{"mapId":"189531148"}},{"mapId":"189530635","area":"Astrub","areaId":18,"subArea":"Forêt d'Astrub","subAreaId":97,"left":{"mapId":"189530123"},"right":{"mapId":"189531147"},"top":{"mapId":"189530634"},"bottom":{"mapId":"189530636"}},{"mapId":"189530636","area":"Astrub","areaId":18,"subArea":"Forêt d'Astrub","subAreaId":97,"left":{"mapId":"189530124"},"right":{"mapId":"189531148"},"top":{"mapId":"189530635"},"bottom":{"mapId":"189530637"}},{"mapId":"189531148","area":"Astrub","areaId":18,"subArea":"Forêt d'Astrub","subAreaId":97,"left":{"mapId":"189530636"},"right":{"mapId":"188743685"},"top":{"mapId":"189531147"},"bottom":{"mapId":"189531149"}},{"mapId":"189531146","area":"Astrub","areaId":18,"subArea":"Forêt d'Astrub","subAreaId":97,"left":{"mapId":"189530634"},"right":{"mapId":"188743683"},"top":{"mapId":"189531145"},"bottom":{"mapId":"189531147"}},{"mapId":"189531145","area":"Astrub","areaId":18,"subArea":"Forêt d'Astrub","subAreaId":97,"left":{"mapId":"189530633"},"right":{"mapId":"188743682"},"top":{"mapId":"189531144"},"bottom":{"mapId":"189531146"}},{"mapId":"189530633","area":"Astrub","areaId":18,"subArea":"Forêt d'Astrub","subAreaId":97,"left":{"mapId":"189530121"},"right":{"mapId":"189531145"},"top":{"mapId":"189530632"},"bottom":{"mapId":"189530634"}},{"mapId":"189531144","area":"Astrub","areaId":18,"subArea":"Forêt d'Astrub","subAreaId":97,"left":{"mapId":"189530632"},"right":{"mapId":"188743681"},"top":{"mapId":"189531143"},"bottom":{"mapId":"189531145"}},{"mapId":"189532167","area":"Astrub","areaId":18,"subArea":"Forêt d'Astrub","subAreaId":97,"left":{"mapId":"189531655"},"right":{"mapId":"189792265"},"top":{"mapId":"189532166"},"bottom":{"mapId":"188744193"}},{"mapId":"189531655","area":"Astrub","areaId":18,"subArea":"Forêt d'Astrub","subAreaId":97,"left":{"mapId":"189531143"},"right":{"mapId":"189532167"},"top":{"mapId":"189531654"},"bottom":{"mapId":"188743681"}},{"mapId":"189532166","area":"Astrub","areaId":18,"subArea":"Forêt d'Astrub","subAreaId":97,"left":{"mapId":"189531654"},"right":{"mapId":"189792264"},"top":{"mapId":"189532165"},"bottom":{"mapId":"189532167"}},{"mapId":"189532165","area":"Astrub","areaId":18,"subArea":"Forêt d'Astrub","subAreaId":97,"left":{"mapId":"189531653"},"right":{"mapId":"189792263"},"top":{"mapId":"189532164"},"bottom":{"mapId":"189532166"}},{"mapId":"189532164","area":"Astrub","areaId":18,"subArea":"Forêt d'Astrub","subAreaId":97,"left":{"mapId":"189531652"},"right":{"mapId":"189792262"},"top":{"mapId":"189532163"},"bottom":{"mapId":"189532165"}},{"mapId":"189532163","area":"Astrub","areaId":18,"subArea":"Forêt d'Astrub","subAreaId":97,"left":{"mapId":"189531651"},"right":{"mapId":"189792261"},"top":{"mapId":"189532162"},"bottom":{"mapId":"189532164"}},{"mapId":"189532162","area":"Astrub","areaId":18,"subArea":"Forêt d'Astrub","subAreaId":97,"left":{"mapId":"189531650"},"right":{"mapId":"189792260"},"top":{"mapId":"189532161"},"bottom":{"mapId":"189532163"}},{"mapId":"189532161","area":"Astrub","areaId":18,"subArea":"Forêt d'Astrub","subAreaId":97,"left":{"mapId":"189531649"},"right":{"mapId":"189792259"},"top":{"mapId":"189532160"},"bottom":{"mapId":"189532162"}},{"mapId":"189532160","area":"Astrub","areaId":18,"subArea":"Forêt d'Astrub","subAreaId":97,"right":{"mapId":"189792258"},"top":{"mapId":"189532417"},"bottom":{"mapId":"189532161"}},{"mapId":"189532417","area":"Astrub","areaId":18,"subArea":"Forêt d'Astrub","subAreaId":97,"right":{"mapId":"189792257"},"bottom":{"mapId":"189532160"}},{"mapId":"189530121","area":"Astrub","areaId":18,"subArea":"Forêt d'Astrub","subAreaId":97,"left":{"mapId":"189661705"},"right":{"mapId":"189530633"},"top":{"mapId":"189530120"},"bottom":{"mapId":"189530122"}},{"mapId":"189661705","area":"Astrub","areaId":18,"subArea":"Forêt d'Astrub","subAreaId":97,"left":{"mapId":"84805634"},"right":{"mapId":"189530121"},"top":{"mapId":"189661704"},"bottom":{"mapId":"189661706"}},{"mapId":"189661704","area":"Astrub","areaId":18,"subArea":"Forêt d'Astrub","subAreaId":97,"left":{"mapId":"84805633"},"right":{"mapId":"189530120"},"top":{"mapId":"189661703"},"bottom":{"mapId":"189661705"}},{"mapId":"189530120","area":"Astrub","areaId":18,"subArea":"Forêt d'Astrub","subAreaId":97,"left":{"mapId":"189661704"},"right":{"mapId":"189530632"},"top":{"mapId":"189530119"},"bottom":{"mapId":"189530121"}},{"mapId":"189530122","area":"Astrub","areaId":18,"subArea":"Forêt d'Astrub","subAreaId":97,"left":{"mapId":"189661706"},"right":{"mapId":"189530634"},"top":{"mapId":"189530121"},"bottom":{"mapId":"189530123"}},{"mapId":"189661706","area":"Astrub","areaId":18,"subArea":"Forêt d'Astrub","subAreaId":97,"left":{"mapId":"165156880"},"right":{"mapId":"189530122"},"top":{"mapId":"189661705"},"bottom":{"mapId":"189661707"}},{"mapId":"189661707","area":"Astrub","areaId":18,"subArea":"Forêt d'Astrub","subAreaId":97,"left":{"mapId":"147854595"},"right":{"mapId":"189530123"},"top":{"mapId":"189661706"},"bottom":{"mapId":"189661708"}},{"mapId":"189530123","area":"Astrub","areaId":18,"subArea":"Forêt d'Astrub","subAreaId":97,"left":{"mapId":"189661707"},"right":{"mapId":"189530635"},"top":{"mapId":"189530122"},"bottom":{"mapId":"189530124"}},{"mapId":"189530634","area":"Astrub","areaId":18,"subArea":"Forêt d'Astrub","subAreaId":97,"left":{"mapId":"189530122"},"right":{"mapId":"189531146"},"top":{"mapId":"189530633"},"bottom":{"mapId":"189530635"}},{"mapId":"189530124","area":"Astrub","areaId":18,"subArea":"Forêt d'Astrub","subAreaId":97,"left":{"mapId":"189661708"},"right":{"mapId":"189530636"},"top":{"mapId":"189530123"},"bottom":{"mapId":"189530125"}},{"mapId":"189530637","area":"Astrub","areaId":18,"subArea":"Forêt d'Astrub","subAreaId":97,"left":{"mapId":"189530125"},"right":{"mapId":"189531149"},"top":{"mapId":"189530636"},"bottom":{"mapId":"189530638"}},{"mapId":"189530125","area":"Astrub","areaId":18,"subArea":"Forêt d'Astrub","subAreaId":97,"left":{"mapId":"189661709"},"right":{"mapId":"189530637"},"top":{"mapId":"189530124"},"bottom":{"mapId":"189530126"}},{"mapId":"189661708","area":"Astrub","areaId":18,"subArea":"Forêt d'Astrub","subAreaId":97,"left":{"mapId":"147854594"},"right":{"mapId":"189530124"},"top":{"mapId":"189661707"},"bottom":{"mapId":"189661709"}},{"mapId":"189661709","area":"Astrub","areaId":18,"subArea":"Forêt d'Astrub","subAreaId":97,"left":{"mapId":"189661710"},"right":{"mapId":"189530125"},"top":{"mapId":"189661708"},"bottom":{"mapId":"189661710"}},{"mapId":"189530126","area":"Astrub","areaId":18,"subArea":"Forêt d'Astrub","subAreaId":97,"left":{"mapId":"189661710"},"right":{"mapId":"189530638"},"top":{"mapId":"189530125"},"bottom":{"mapId":"189530634"}},{"mapId":"189661710","area":"Astrub","areaId":18,"subArea":"Forêt d'Astrub","subAreaId":97,"left":{"mapId":"147854336"},"right":{"mapId":"189530126"},"top":{"mapId":"189661709"},"bottom":{"mapId":"189530126"}},{"mapId":"189530638","area":"Astrub","areaId":18,"subArea":"Forêt d'Astrub","subAreaId":97,"left":{"mapId":"189530126"},"right":{"mapId":"189531150"},"top":{"mapId":"189530637"},"bottom":{"mapId":"190841856"}},{"mapId":"189530632","area":"Astrub","areaId":18,"subArea":"Forêt d'Astrub","subAreaId":97,"left":{"mapId":"189530120"},"right":{"mapId":"189531144"},"top":{"mapId":"189530631"},"bottom":{"mapId":"189530633"}},{"mapId":"189530119","area":"Astrub","areaId":18,"subArea":"Forêt d'Astrub","subAreaId":97,"left":{"mapId":"189661703"},"right":{"mapId":"189530631"},"top":{"mapId":"189530118"},"bottom":{"mapId":"189530120"}},{"mapId":"189661703","area":"Astrub","areaId":18,"subArea":"Forêt d'Astrub","subAreaId":97,"left":{"mapId":"84805632"},"right":{"mapId":"189530119"},"top":{"mapId":"84805377"},"bottom":{"mapId":"189661704"}},{"mapId":"189530118","area":"Astrub","areaId":18,"subArea":"Forêt d'Astrub","subAreaId":97,"left":{"mapId":"84805377"},"right":{"mapId":"189530630"},"top":{"mapId":"189530117"},"bottom":{"mapId":"189530119"}},{"mapId":"189530630","area":"Astrub","areaId":18,"subArea":"Forêt d'Astrub","subAreaId":97,"left":{"mapId":"189530118"},"right":{"mapId":"189531142"},"top":{"mapId":"189530629"},"bottom":{"mapId":"189530631"}},{"mapId":"189531142","area":"Astrub","areaId":18,"subArea":"Forêt d'Astrub","subAreaId":97,"left":{"mapId":"189530630"},"right":{"mapId":"189531654"},"top":{"mapId":"189531141"},"bottom":{"mapId":"189531143"}},{"mapId":"189531654","area":"Astrub","areaId":18,"subArea":"Forêt d'Astrub","subAreaId":97,"left":{"mapId":"189531142"},"right":{"mapId":"189532166"},"top":{"mapId":"189531653"},"bottom":{"mapId":"189531655"}},{"mapId":"189531649","area":"Astrub","areaId":18,"subArea":"Forêt d'Astrub","subAreaId":97,"left":{"mapId":"189531137"},"right":{"mapId":"189532161"},"bottom":{"mapId":"189531650"}},{"mapId":"189531137","area":"Astrub","areaId":18,"subArea":"Forêt d'Astrub","subAreaId":97,"left":{"mapId":"189530625"},"right":{"mapId":"189531649"},"bottom":{"mapId":"189531138"}},{"mapId":"189530625","area":"Astrub","areaId":18,"subArea":"Forêt d'Astrub","subAreaId":97,"left":{"mapId":"189530113"},"right":{"mapId":"189531137"},"bottom":{"mapId":"189530626"}},{"mapId":"189530113","area":"Astrub","areaId":18,"subArea":"Forêt d'Astrub","subAreaId":97,"left":{"mapId":"84805382"},"right":{"mapId":"189530625"},"top":{"mapId":"189530112"},"bottom":{"mapId":"189530114"}},{"mapId":"189530114","area":"Astrub","areaId":18,"subArea":"Forêt d'Astrub","subAreaId":97,"left":{"mapId":"84805381"},"right":{"mapId":"189530626"},"top":{"mapId":"189530113"},"bottom":{"mapId":"189530115"}},{"mapId":"189530626","area":"Astrub","areaId":18,"subArea":"Forêt d'Astrub","subAreaId":97,"left":{"mapId":"189530114"},"right":{"mapId":"189531138"},"top":{"mapId":"189530625"},"bottom":{"mapId":"189530627"}},{"mapId":"189531138","area":"Astrub","areaId":18,"subArea":"Forêt d'Astrub","subAreaId":97,"left":{"mapId":"189530626"},"right":{"mapId":"189531650"},"top":{"mapId":"189531137"},"bottom":{"mapId":"189531139"}},{"mapId":"189531650","area":"Astrub","areaId":18,"subArea":"Forêt d'Astrub","subAreaId":97,"left":{"mapId":"189531138"},"right":{"mapId":"189532162"},"top":{"mapId":"189531649"},"bottom":{"mapId":"189531651"}},{"mapId":"189531651","area":"Astrub","areaId":18,"subArea":"Forêt d'Astrub","subAreaId":97,"left":{"mapId":"189531139"},"right":{"mapId":"189532163"},"top":{"mapId":"189531650"},"bottom":{"mapId":"189531652"}},{"mapId":"189531139","area":"Astrub","areaId":18,"subArea":"Forêt d'Astrub","subAreaId":97,"left":{"mapId":"189530627"},"right":{"mapId":"189531651"},"top":{"mapId":"189531138"},"bottom":{"mapId":"189531140"}},{"mapId":"189530627","area":"Astrub","areaId":18,"subArea":"Forêt d'Astrub","subAreaId":97,"left":{"mapId":"189530115"},"right":{"mapId":"189531139"},"top":{"mapId":"189530626"},"bottom":{"mapId":"189530628"}},{"mapId":"189530115","area":"Astrub","areaId":18,"subArea":"Forêt d'Astrub","subAreaId":97,"left":{"mapId":"84805380"},"right":{"mapId":"189530627"},"top":{"mapId":"189530114"},"bottom":{"mapId":"189530116"}},{"mapId":"189530116","area":"Astrub","areaId":18,"subArea":"Forêt d'Astrub","subAreaId":97,"left":{"mapId":"84805379"},"right":{"mapId":"189530628"},"top":{"mapId":"189530115"},"bottom":{"mapId":"189530117"}},{"mapId":"189530628","area":"Astrub","areaId":18,"subArea":"Forêt d'Astrub","subAreaId":97,"left":{"mapId":"189530116"},"right":{"mapId":"189531140"},"top":{"mapId":"189530627"},"bottom":{"mapId":"189530629"}},{"mapId":"189531140","area":"Astrub","areaId":18,"subArea":"Forêt d'Astrub","subAreaId":97,"left":{"mapId":"189530628"},"right":{"mapId":"189531652"},"top":{"mapId":"189531139"},"bottom":{"mapId":"189531141"}},{"mapId":"189531652","area":"Astrub","areaId":18,"subArea":"Forêt d'Astrub","subAreaId":97,"left":{"mapId":"189531140"},"right":{"mapId":"189532164"},"top":{"mapId":"189531651"},"bottom":{"mapId":"189531653"}},{"mapId":"189531653","area":"Astrub","areaId":18,"subArea":"Forêt d'Astrub","subAreaId":97,"left":{"mapId":"189531141"},"right":{"mapId":"189532165"},"top":{"mapId":"189531652"},"bottom":{"mapId":"189531654"}},{"mapId":"189531143","area":"Astrub","areaId":18,"subArea":"Forêt d'Astrub","subAreaId":97,"left":{"mapId":"189530631"},"right":{"mapId":"189531655"},"top":{"mapId":"189531142"},"bottom":{"mapId":"189531144"}},{"mapId":"189531141","area":"Astrub","areaId":18,"subArea":"Forêt d'Astrub","subAreaId":97,"left":{"mapId":"189530629"},"right":{"mapId":"189531653"},"top":{"mapId":"189531140"},"bottom":{"mapId":"189531142"}},{"mapId":"189530629","area":"Astrub","areaId":18,"subArea":"Forêt d'Astrub","subAreaId":97,"left":{"mapId":"189530117"},"right":{"mapId":"189531141"},"top":{"mapId":"189530628"},"bottom":{"mapId":"189530630"}},{"mapId":"189530631","area":"Astrub","areaId":18,"subArea":"Forêt d'Astrub","subAreaId":97,"left":{"mapId":"189530119"},"right":{"mapId":"189531143"},"top":{"mapId":"189530630"},"bottom":{"mapId":"189530632"}},{"mapId":"189530117","area":"Astrub","areaId":18,"subArea":"Forêt d'Astrub","subAreaId":97,"left":{"mapId":"84805378"},"right":{"mapId":"189530629"},"top":{"mapId":"189530116"},"bottom":{"mapId":"189530118"}},{"mapId":"189530112","area":"Astrub","areaId":18,"subArea":"Forêt d'Astrub","subAreaId":97,"left":{"mapId":"126092288"},"right":{"mapId":"120061958"},"top":{"mapId":"120193541"},"bottom":{"mapId":"189530113"}}]