[{"mapId":"212599303","area":"Bonta","subArea":"Havres d'ivoire","right":{"mapId":"212599815"},"top":{"mapId":"212599302"}},{"mapId":"212599302","area":"Bonta","subArea":"Havres d'ivoire","left":{"mapId":"212598790"},"bottom":{"mapId":"212599303"}},{"mapId":"212598790","area":"Bonta","subArea":"Havres d'ivoire","left":{"mapId":"212730374"},"right":{"mapId":"212599302"}},{"mapId":"212730374","area":"Bonta","subArea":"Havres d'ivoire","right":{"mapId":"212598790"},"top":{"mapId":"212730373"}},{"mapId":"212730373","area":"Bonta","subArea":"Havres d'ivoire","left":{"mapId":"212731910"},"right":{"mapId":"212598789"},"bottom":{"mapId":"212730374"}},{"mapId":"212731910","area":"Bonta","subArea":"Havres d'ivoire","right":{"mapId":"212730373"}},{"mapId":"212598789","area":"Bonta","subArea":"Havres d'ivoire","left":{"mapId":"212730373"},"right":{"mapId":"212599301"},"bottom":{"mapId":"212598790"}},{"mapId":"212599301","area":"Bonta","subArea":"Havres d'ivoire","left":{"mapId":"212598789"},"right":{"mapId":"212599813"},"bottom":{"mapId":"212599302"}}]