[{"mapId":"84542210","area":"Amakna","subArea":"Presqu'île des Dragoeufs","right":{"mapId":"84410626"},"top":{"mapId":"221643270"}},{"mapId":"84410626","area":"Amakna","subArea":"Presqu'île des Dragoeufs","left":{"mapId":"84542210"},"top":{"mapId":"221511686"},"bottom":{"mapId":"84410625"}},{"mapId":"84410625","area":"Amakna","subArea":"Presqu'île des Dragoeufs","left":{"mapId":"84542209"},"top":{"mapId":"84410626"}},{"mapId":"84542209","area":"Amakna","subArea":"Presqu'île des Dragoeufs","right":{"mapId":"84410625"},"top":{"mapId":"84542210"},"bottom":{"mapId":"84541952"}},{"mapId":"84541952","area":"Amakna","subArea":"Presqu'île des Dragoeufs","top":{"mapId":"84542209"},"bottom":{"mapId":"84541953"}},{"mapId":"84541953","area":"Amakna","subArea":"Presqu'île des Dragoeufs","right":{"mapId":"84410369"},"top":{"mapId":"84541952"}},{"mapId":"84410369","area":"Amakna","subArea":"Presqu'île des Dragoeufs","left":{"mapId":"84541953"},"right":{"mapId":"84410881"}}]