[{"mapId":"126092288","area":"Plaines de Cania","areaId":8,"subArea":"Plaine des Porkass","subAreaId":178,"right":{"mapId":"189530112"}},{"mapId":"84805382","area":"Plaines de Cania","areaId":8,"subArea":"Plaine des Porkass","subAreaId":178,"right":{"mapId":"189530113"}},{"mapId":"84805381","area":"Plaines de Cania","areaId":8,"subArea":"Plaine des Porkass","subAreaId":178,"right":{"mapId":"189530114"}},{"mapId":"84805380","area":"Plaines de Cania","areaId":8,"subArea":"Plaine des Porkass","subAreaId":178,"right":{"mapId":"189530115"}},{"mapId":"84805379","area":"Plaines de Cania","areaId":8,"subArea":"Plaine des Porkass","subAreaId":178,"right":{"mapId":"189530116"}},{"mapId":"84805378","area":"Plaines de Cania","areaId":8,"subArea":"Plaine des Porkass","subAreaId":178,"right":{"mapId":"189530117"}},{"mapId":"84805377","area":"Plaines de Cania","areaId":8,"subArea":"Plaine des Porkass","subAreaId":178,"right":{"mapId":"189530118"},"bottom":{"mapId":"189661703"}},{"mapId":"84805632","area":"Plaines de Cania","areaId":8,"subArea":"Plaine des Porkass","subAreaId":178,"right":{"mapId":"189661703"}},{"mapId":"84805633","area":"Plaines de Cania","areaId":8,"subArea":"Plaine des Porkass","subAreaId":178,"right":{"mapId":"189661704"}},{"mapId":"84805634","area":"Plaines de Cania","areaId":8,"subArea":"Plaine des Porkass","subAreaId":178,"right":{"mapId":"189661705"}},{"mapId":"165156880","area":"Plaines de Cania","areaId":8,"subArea":"Plaine des Porkass","subAreaId":178,"right":{"mapId":"189661706"}}]