[{"mapId":"159650321","area":"Bonta","subArea":"Rives iridescentes","left":{"mapId":"159649809"},"bottom":{"mapId":"142089219"}},{"mapId":"159649809","area":"Bonta","subArea":"Rives iridescentes","left":{"mapId":"159649297"},"right":{"mapId":"159650321"},"top":{"mapId":"159649808"},"bottom":{"mapId":"142088707"}},{"mapId":"159649297","area":"Bonta","subArea":"Rives iridescentes","left":{"mapId":"159648785"},"right":{"mapId":"159649809"},"bottom":{"mapId":"142088195"}},{"mapId":"159648785","area":"Bonta","subArea":"Rives iridescentes","left":{"mapId":"159648273"},"right":{"mapId":"159649297"},"bottom":{"mapId":"142087683"}},{"mapId":"159648273","area":"Bonta","subArea":"Rives iridescentes","left":{"mapId":"159647761"},"right":{"mapId":"159648785"},"bottom":{"mapId":"142087171"}},{"mapId":"159647761","area":"Bonta","subArea":"Rives iridescentes","left":{"mapId":"159647249"},"right":{"mapId":"159648273"},"bottom":{"mapId":"142086659"}},{"mapId":"159647249","area":"Bonta","subArea":"Rives iridescentes","left":{"mapId":"142085634"},"right":{"mapId":"159647761"},"top":{"mapId":"159647248"},"bottom":{"mapId":"142086147"}},{"mapId":"159777808","area":"Bonta","subArea":"Rives iridescentes","left":{"mapId":"142083073"},"right":{"mapId":"159777296"},"top":{"mapId":"159777807"},"bottom":{"mapId":"142083586"}},{"mapId":"159777296","area":"Bonta","subArea":"Rives iridescentes","left":{"mapId":"159777808"},"right":{"mapId":"159645712"},"bottom":{"mapId":"142084098"}},{"mapId":"159645712","area":"Bonta","subArea":"Rives iridescentes","left":{"mapId":"159777296"},"right":{"mapId":"159646224"},"bottom":{"mapId":"142084610"}},{"mapId":"159646224","area":"Bonta","subArea":"Rives iridescentes","left":{"mapId":"159645712"},"right":{"mapId":"159646736"},"bottom":{"mapId":"142085122"}},{"mapId":"159646736","area":"Bonta","subArea":"Rives iridescentes","left":{"mapId":"159646224"},"right":{"mapId":"159647248"},"bottom":{"mapId":"142085634"}},{"mapId":"159647248","area":"Bonta","subArea":"Rives iridescentes","left":{"mapId":"159646736"},"bottom":{"mapId":"159647249"}},{"mapId":"159777807","area":"Bonta","subArea":"Rives iridescentes","left":{"mapId":"159778319"},"bottom":{"mapId":"159777808"}},{"mapId":"159778319","area":"Bonta","subArea":"Rives iridescentes","left":{"mapId":"159778831"},"right":{"mapId":"159777807"},"bottom":{"mapId":"142083073"}},{"mapId":"159778831","area":"Bonta","subArea":"Rives iridescentes","left":{"mapId":"159779343"},"right":{"mapId":"159778319"},"bottom":{"mapId":"142082561"}},{"mapId":"159779343","area":"Bonta","subArea":"Rives iridescentes","right":{"mapId":"159778831"},"bottom":{"mapId":"142082049"}},{"mapId":"159649808","area":"Bonta","subArea":"Rives iridescentes","left":{"mapId":"212603916"},"bottom":{"mapId":"159649809"}},{"mapId":"212603916","area":"Bonta","subArea":"Faubourgs des artisans","left":{"mapId":"212603914"}},{"mapId":"212603914","area":"Bonta","subArea":"Faubourgs des artisans","left":{"mapId":"212602890"}},{"mapId":"212602890","area":"Bonta","subArea":"Faubourgs des artisans","left":{"mapId":"212602376"}},{"mapId":"212602376","area":"Bonta","subArea":"Faubourgs des artisans","left":{"mapId":"212601864"},"top":{"mapId":"212602375"}},{"mapId":"212601864","area":"Bonta","subArea":"Faubourgs des artisans","left":{"mapId":"212600839"},"right":{"mapId":"212602376"}},{"mapId":"212600839","area":"Bonta","subArea":"Faubourgs des artisans","left":{"mapId":"212600327"},"right":{"mapId":"212601864"}},{"mapId":"212600327","area":"Bonta","subArea":"Faubourgs des artisans","left":{"mapId":"212599815"},"right":{"mapId":"212600839"}},{"mapId":"212599815","area":"Bonta","subArea":"Faubourgs des artisans","left":{"mapId":"212599303"},"right":{"mapId":"212600327"}},{"mapId":"212599303","area":"Bonta","subArea":"Havres d'ivoire","right":{"mapId":"212599815"},"top":{"mapId":"212599302"}},{"mapId":"212599302","area":"Bonta","subArea":"Havres d'ivoire","left":{"mapId":"212598790"},"bottom":{"mapId":"212599303"}},{"mapId":"212598790","area":"Bonta","subArea":"Havres d'ivoire","left":{"mapId":"212730374"},"right":{"mapId":"212599302"}},{"mapId":"212730374","area":"Bonta","subArea":"Havres d'ivoire","right":{"mapId":"212598790"},"top":{"mapId":"212730373"}},{"mapId":"212730373","area":"Bonta","subArea":"Havres d'ivoire","left":{"mapId":"212731910"},"right":{"mapId":"212598789"},"bottom":{"mapId":"212730374"}},{"mapId":"212731910","area":"Bonta","subArea":"Havres d'ivoire","right":{"mapId":"212730373"}},{"mapId":"212598789","area":"Bonta","subArea":"Havres d'ivoire","left":{"mapId":"212730373"},"right":{"mapId":"212599301"},"bottom":{"mapId":"212598790"}},{"mapId":"212599301","area":"Bonta","subArea":"Havres d'ivoire","left":{"mapId":"212598789"},"right":{"mapId":"212599813"},"bottom":{"mapId":"212599302"}},{"mapId":"212599813","area":"Bonta","subArea":"Faubourgs des artisans","left":{"mapId":"212599301"},"right":{"mapId":"212600325"}},{"mapId":"212600325","area":"Bonta","subArea":"Faubourgs des artisans","left":{"mapId":"212599813"},"right":{"mapId":"212600837"}},{"mapId":"212600837","area":"Bonta","subArea":"Faubourgs des artisans","left":{"mapId":"212600325"},"right":{"mapId":"212601349"}},{"mapId":"212601349","area":"Bonta","subArea":"Faubourgs des artisans","left":{"mapId":"212600837"},"right":{"mapId":"212601861"}},{"mapId":"212601861","area":"Bonta","subArea":"Faubourgs des artisans","left":{"mapId":"212601349"},"right":{"mapId":"212602886"},"top":{"mapId":"212601860"},"bottom":{"mapId":"212602375"}},{"mapId":"212602886","area":"Bonta","subArea":"Faubourgs des artisans","left":{"mapId":"212601861"},"top":{"mapId":"212602885"},"bottom":{"mapId":"212602887"}},{"mapId":"212602885","area":"Bonta","subArea":"Faubourgs des artisans","bottom":{"mapId":"212602886"}},{"mapId":"212602887","area":"Bonta","subArea":"Faubourgs des artisans","left":{"mapId":"212602375"},"top":{"mapId":"212602886"}},{"mapId":"212602375","area":"Bonta","subArea":"Faubourgs des artisans","right":{"mapId":"212602887"},"top":{"mapId":"212601861"},"bottom":{"mapId":"212602376"}},{"mapId":"212601860","area":"Bonta","subArea":"Faubourgs des artisans","left":{"mapId":"212601348"},"bottom":{"mapId":"212601861"}},{"mapId":"212601348","area":"Bonta","subArea":"Faubourgs des artisans","right":{"mapId":"212601860"},"top":{"mapId":"212601347"},"bottom":{"mapId":"212601349"}},{"mapId":"212601347","area":"Bonta","subArea":"Faubourgs des artisans","right":{"mapId":"212601859"},"bottom":{"mapId":"212601348"}},{"mapId":"212601859","area":"Bonta","subArea":"Faubourgs des artisans","left":{"mapId":"212601347"},"top":{"mapId":"212601858"},"bottom":{"mapId":"212601860"}},{"mapId":"212601858","area":"Bonta","subArea":"Faubourgs des artisans","left":{"mapId":"212601346"},"bottom":{"mapId":"212601859"}},{"mapId":"212601346","area":"Bonta","subArea":"Faubourgs des artisans","left":{"mapId":"212600321"},"right":{"mapId":"212601858"},"bottom":{"mapId":"212601347"}},{"mapId":"212600321","area":"Bonta","subArea":"Cœur immaculé","left":{"mapId":"212599809"},"right":{"mapId":"212601346"}},{"mapId":"212599809","area":"Bonta","subArea":"Cœur immaculé","right":{"mapId":"212600321"}}]